attribute_standardizer/__init__.py
attribute_standardizer/_version.py
attribute_standardizer/attribute_standardizer.py
attribute_standardizer/const.py
attribute_standardizer/model.py
attribute_standardizer/utils.py
attribute_standardizer-0.1.1.dist-info/LICENSE.txt
attribute_standardizer-0.1.1.dist-info/METADATA
attribute_standardizer-0.1.1.dist-info/WHEEL
attribute_standardizer-0.1.1.dist-info/top_level.txt
attribute_standardizer-0.1.1.dist-info/RECORD
