Metadata-Version: 2.1
Name: attribute-standardizer
Version: 0.1.1
Summary: BEDMess attribute standardizer for metadata attribute standardization
Home-page: https://github.com/databio/bedmess/
Author: Saanika Tambe
License: BSD2
Keywords: project,metadata,bioinformatics
Classifier: Development Status :: 4 - Beta
Classifier: License :: OSI Approved :: BSD License
Classifier: Programming Language :: Python :: 3.8
Classifier: Programming Language :: Python :: 3.9
Classifier: Programming Language :: Python :: 3.10
Classifier: Programming Language :: Python :: 3.11
Classifier: Programming Language :: Python :: 3.12
Classifier: Topic :: Scientific/Engineering :: Bio-Informatics
License-File: LICENSE.txt
Requires-Dist: pandas
Requires-Dist: numpy
Requires-Dist: torch
Requires-Dist: transformers
Requires-Dist: pephubclient
